[{"q":"Biến con trỏ có thể chứa","a":"Địa chỉ vùng nhớ của một biến khác."},{"q":"Biểu thức điều kiện để kiểm tra một phần tử thứ i của mảng A có nằm trong (-5;10) là ?\n1. (A[i]  >  -5) and (A[i]  <  10)\n2. (-5  <  A[i]) and (10  <  A[i])","a":"1 đúng, 2 đúng"},{"q":"Char S[20]=\"aaaaaea\";\n\nchar* p=strstr(S,\"e\");\n\nNếu địa chỉ của S là 1000, thì giá trị của p là bao nhiêu là","a":"1005"},{"q":"Cho Stack gồm 5 phần tử {12, 5, 20, 23, 25}, trong đó 25 là phần tử ở đỉnh Stack. Để lấy ra phần tử thứ 3 trong Stack ta phải làm thế nào?","a":"POP(25), POP(23), POP(20), PUSH(23), PUSH(25)"},{"q":"Cho Stack gồm 5 phần tử {12, 5, 20, 23, 25}, trong đó 25 là phần tử ở đỉnh Stack. Để lấy ra phần tử thứ 4 trong Stack ta phải làm thế nào?","a":["POP(23)","POP(25),","PUSH(25)"]},{"q":"Cho biết đoạn chương trình sau có kết quả bao nhiêu:  \n\nvoid main()\n\n{\n\n int ints[] = { 0, 1, 2, 3 };\n\n int* i1 = ints + 1;\n\n int a = ++*i1;\n\n int b = a + *i1;\n\n printf(\"%d\\n\", b);\n\n getch();\n\n}","a":"4"},{"q":"Cho cây nhị phân T có 70 nút cấp 2 ( có 2 con).Cây đó có bao nhiêu nút lá( không có con):","a":"71"},{"q":"Cho cây nhị phân T có chiều cao là 6( nút gốc có mức 1) . Số nút tối đa của cây là:","a":"63"},{"q":"Cho cây nhị phân T, nút có địa chỉ 19 thì có nút cha ở địa chỉ nào","a":"9"},{"q":"Cho cây nhị phân T, nút có địa chỉ 7 có 2 con ở địa chỉ nào:","a":["14","15"]},{"q":"Cho cây nhị phân T, phép duỵêt cây theo thứ tự giữa cho kết quả DBHEAFICGJ . Nếu duyệt theo thứ tự sau ta có kết quả : DHEBIFJGCA . Hãy cho biết các nút của cây con phải","a":"ficgj"},{"q":"Cho cây nhị phân T. Phép duyệt cây theo thứ tự trước cho kết quả ABDEHCFIGJ. Nếu duyệt theo thứ tự giữa ta có kết quả: DBHEAFICGJ. Hãy cho biết các nút của cây con trái","a":"bdhe"},{"q":"Cho cây nhị phân T. Phép duyệt thứ tự trước cho kết quả là","a":"abdecfg"},{"q":"Cho cấu trúc dữ liệu như sau:\n\nstruct Employee\n\n{ char Code[], name[];\n\n long Salary;\n\n};\n\nEmployee e1= { \"E089\", \"Hoang so\", 12000}, e2=e1;\n\nprintf(\"%ld\",el.Salary+e2 - >  Salary); cho biết kết quả của chương trình","a":"doan-ma-bi-loi"},{"q":"Cho dãy khoá 42,23,74,11,65,58,94,36\nLần lượt đưa dãy khoá trên vào cây nhị phân tìm kiếm. Bây giờ ta muốn tìm kiếm xem trong dãy khoá trên có khoá 105 không thì phải làm bao nhiêu phép so sánh:","a":"3"},{"q":"Cho dãy khoá 42,23,74,11,65,58,94,36\nLần lượt đưa dãy khoá trên vào cây nhị phân tìm kiếm. Nếu ta tìm kiếm trên cây nhị phân này thì trong trường hợp xấu nhất phải làm bao nhiêu phép so sánh","a":"4"},{"q":"Cho dãy số 27 40 -7 5 57, thực hiện bước thứ 1, khi áp dụng thuật toán sắp xếp lựa chọn để sắp xếp dãy theo thứ tự giảm, ta có được dãy mới là gì?","a":"57  27 -7  5  40"},{"q":"Cho dãy số sau: 10 11 14 32 36 43 55 57 87 97. Áp dụng phương pháp tìm kiếm nhị phân, để tìm kiếm số 10, lần phân đoạn thứ nhất của dãy sẽ là","a":"[10 11 14 32 36]"},{"q":"Cho dãy số sau: 14 32 10 43 57 87 55 36 97 11. Áp dụng phương pháp tìm kiếm tuần tự, sau bao nhiều lần thực hiện phép so sánh ta sẽ tìm thấy số 43?","a":"4 lần"},{"q":"Cho dãy số sau: 40 25 75 15 65 55 90 30 95 85. Áp dụng phương pháp sắp xếp lựa chọn, sau lượt 1 dãy sẽ được sắp xếp lại như thế nào?","a":"15 25 75 40 65 55 90 30 95 85"},{"q":"Cho dãy số sau: 40 25 75 15 65 55 90 30 95 85. Áp dụng phương pháp sắp xếp lựa chọn, sau lượt 2 dãy sẽ được sắp xếp lại như thế nào?","a":"15 25 75 40 65 55 90 30 95 85"},{"q":"Cho dãy số sau: 40 25 75 15 65 55 90 30 95 85. Áp dụng phương pháp sắp xếp lựa chọn, sau lượt 3 dãy sẽ được sắp xếp lại như thế nào?","a":"15 25 30 40 65 55 90 75 95 85"},{"q":"Cho dãy số sau: 40 25 75 15 65 55 90 30 95 85. Áp dụng phương pháp sắp xếp nhanh (Quick_Sort), sau lượt 6 dãy sẽ được sắp xếp lại như thế nào?","a":"1 5 25 30 40 55 65 (90 75 95 85)"},{"q":"Cho dãy số {3 1 6 0 5 4 8 2 9 7}. áp dụng phương pháp sắp xếp nhanh (Quick sort) sau lần lặp đầu tiên của giải thuật ta có kết quả: {(0 1 2) 3 (5 4 8 6 9 7)}. Dãy số thu được sau lần lặp thứ ba là:","a":"{0-1-(2)-3-(5-4-8-6-9-7)}"},{"q":"Cho dãy số {3 1 6 0 5 4 8 2 9 7}. áp dụng phương pháp sắp xếp nhanh (Quick sort) sau lần lặp đầu tiên của giải thuật ta có kết quả: {(0 1 2) 3 (5 4 8 6 9 7)}. Dãy số thu được sau lần lặp thứ bốn là:","a":"{0-1-2-3-(5-4-8-6-9-7)}"},{"q":"Cho dãy số {4 0 2 8 5 9 6 1 3 7}. áp dụng phương pháp sắp xếp chèn (Insert sort) sau lần lặp đầu tiên của giải thuật ta có kết quả:{0 4 2 8 5 9 6 1 3 7}. Dãy số thu được sau lần lặp thứ ba là:","a":"{0-2-4-8-5-9-6-1-3-7}"},{"q":"Cho dãy số {4 0 2 8 5 9 6 1 3 7}. áp dụng phương pháp sắp xếp chèn (Insert sort) sau lần lặp đầu tiên của giải thuật ta có kết quả:{0 4 2 8 5 9 6 1 3 7}. Dãy số thu được sau lần lặp thứ bảy là:","a":"{0-1-2-4-5-6-8-9-3-7}"},{"q":"Cho dãy số {4 0 2 8 5 9 6 1 3 7}. áp dụng phương pháp sắp xếp chèn (Insert sort) sau lần lặp đầu tiên của giải thuật ta có kết quả:{0 4 2 8 5 9 6 1 3 7}. Dãy số thu được sau lần lặp thứ bốn là:","a":"{0-2-4-5-8-9-6-1-3-7}"},{"q":"Cho dãy số {4 0 2 8 5 9 6 1 3 7}. áp dụng phương pháp sắp xếp chèn (Insert sort) sau lần lặp đầu tiên của giải thuật ta có kết quả:{0 4 2 8 5 9 6 1 3 7}. Dãy số thu được sau lần lặp thứ chín là:","a":"{0-1-2-3-4-5-6-7-8-9}"},{"q":"Cho dãy số {4 0 2 8 5 9 6 1 3 7}. áp dụng phương pháp sắp xếp chèn (Insert sort) sau lần lặp đầu tiên của giải thuật ta có kết quả:{0 4 2 8 5 9 6 1 3 7}. Dãy số thu được sau lần lặp thứ hai là:","a":"{0-2-4-8-5-9-6-1-3-7}"},{"q":"Cho dãy số {4 0 2 8 5 9 6 1 3 7}. áp dụng phương pháp sắp xếp chèn (Insert sort) sau lần lặp đầu tiên của giải thuật ta có kết quả:{0 4 2 8 5 9 6 1 3 7}. Dãy số thu được sau lần lặp thứ tám là:","a":"{0-1-2-3-4-5-6-8-9-7}"},{"q":"Cho dãy số {4 7 0 9 2 5 3 1 8 6}. áp dụng phương pháp sắp xếp nổi bọt (Bubble sort) sau lần lặp đầu tiên của giải thuật ta có kết quả:{0 4 7 1 9 2 5 3 6 8}. Dãy số thu được sau lần lặp thứ ba là:","a":"{0-1-2-4-7-3-9-5-6-8}"},{"q":"Cho dãy số {4 7 0 9 2 5 3 1 8 6}. áp dụng phương pháp sắp xếp nổi bọt (Bubble sort) sau lần lặp đầu tiên của giải thuật ta có kết quả:{0 4 7 1 9 2 5 3 6 8}. Dãy số thu được sau lần lặp thứ bốn là:","a":"{0-1-2-3-4-7-5-9-6-8}"},{"q":"Cho dãy số {4 7 0 9 2 5 3 1 8 6}. áp dụng phương pháp sắp xếp nổi bọt (Bubble sort) sau lần lặp đầu tiên của giải thuật ta có kết quả:{0 4 7 1 9 2 5 3 6 8}. Dãy số thu được sau lần lặp thứ năm là:","a":"{0-1-2-3-4-5-7-6-9-8}"},{"q":"Cho dãy số {6 1 3 0 5 7 9 2 8 4}. áp dụng phương pháp sắp xếp lựa chọn (Select sort) sau lần lặp đầu tiên của giải thuật ta có kết quả: {0 1 3 6 5 7 9 2 8 4}. Dãy số thu được sau lần lặp thứ ba là:","a":"{0 1 2 6 5 7 9 3 8 4}"},{"q":"Cho dãy số {6 1 3 0 5 7 9 2 8 4}. áp dụng phương pháp sắp xếp lựa chọn (Select sort) sau lần lặp đầu tiên của giải thuật ta có kết quả: {0 1 3 6 5 7 9 2 8 4}. Dãy số thu được sau lần lặp thứ bảy là:","a":"{0 1 2 3 4 5 6 9 8 7}"},{"q":"Cho dãy số {6 1 3 0 5 7 9 2 8 4}. áp dụng phương pháp sắp xếp lựa chọn (Select sort) sau lần lặp đầu tiên của giải thuật ta có kết quả: {0 1 3 6 5 7 9 2 8 4}. Dãy số thu được sau lần lặp thứ hai là:","a":"{0 1 3 6 5 7 9 2 8 4}"},{"q":"Cho dãy số {6 1 3 0 5 7 9 2 8 4}. áp dụng phương pháp sắp xếp lựa chọn (Select sort) sau lần lặp đầu tiên của giải thuật ta có kết quả: {0 1 3 6 5 7 9 2 8 4}. Dãy số thu được sau lần lặp thứ năm là:","a":"{0 1 2 3 4 7 9 6 8 5}"},{"q":"Cho dãy số {6 1 3 0 5 7 9 2 8 4}. áp dụng phương pháp sắp xếp lựa chọn (Select sort) sau lần lặp đầu tiên của giải thuật ta có kết quả: {0 1 3 6 5 7 9 2 8 4}. Dãy số thu được sau lần lặp thứ sáu là:","a":"{0 1 2 3 4 5 9 6 8 7}"},{"q":"Cho dãy số {6 1 3 0 5 7 9 2 8 4}. áp dụng phương pháp sắp xếp lựa chọn (Select sort) sau lần lặp đầu tiên của giải thuật ta có kết quả: {0 1 3 6 5 7 9 2 8 4}. Dãy số thu được sau lần lặp thứ tư là:","a":"{0 1 2 3 6 5 7 9 8 4}"},{"q":"Cho dãy số {6 1 3 0 5 7 9 2 8 4}. áp dụng phương pháp sắp xếp lựa chọn (Select sort) tăng dần, sau lần lặp đầu tiên của giải thuật ta có kết quả: {0 1 3 6 5 7 9 2 8 4}. Dãy số thu được sau lần lặp thứ tám là:","a":"{0 1 2 3 4 5 6 7 8 9}"},{"q":"Cho giải thuật sau:\n1.C(n,n)=C(n,0)=1\n2.C(n,k)=C(n-1,k)+C(n-1,k-1) với n > k > 0\nGiá trị của C(4,2) là","a":"6"},{"q":"Cho giải thuật đệ quy\n\n1.F(1)=1, F(2)=2, F(3)=2\n\n2.F(k)=F(K-1) + 2F(K-3) , K > 3\n\nHãy tính F(6)","a":"12"},{"q":"Cho giải thuật đệ quy\n\n1.F(1)=F(2)=1\n\n2.F(k)=F(k-1)+F(k-2) nếu K > 2\n\nHãy tính F(6):","a":"8"},{"q":"Cho giải thuật đệ quy\n1.F(1)=1, F(2)=2, F(3)=2\n2.F(k)=F(K-1) + 2F(K-3) , K > 3\nHãy tính F(6)","a":"12"},{"q":"Cho giải thuật đệ quy\n1.F(1)=F(2)=1\n2.F(k)=F(k-1)+F(k-2) nếu K > 2\nHãy tính F(6):","a":"8"},{"q":"Cho giải thuật đệ quy\n1.F(1)=F(2)=1\n2.F(k)=F(k-1)+F(k-2) nếu K > 2\nHãy tính F(7):","a":"13"},{"q":"Cho giải thuật đệ quy:\n\n1.F(0,a)=F(a,0)=a (0 là số không)\n\n2.F(m,n)=F(m-n,n) nếu m > =n\n\n3.F(m,n)=F(m,n-m) Nếu m=30, n = 75 thì sau khi thực hiện giải thuật ta được giá trị là","a":"15"},{"q":"Cho giải thuật đệ quy:\n1.F(0,a)=F(a,0)=a (0 là số không)\n2.F(m,n)=F(m-n,n) nếu m > =n\n3.F(m,n)=F(m,n-m) Nếu m=30, n = 75 thì sau khi thực hiện giải thuật ta được giá trị là","a":"15"},{"q":"Cho mảng 2 chiều A={F( i j)}: i là chỉ số hàng, j là chỉ số cột. Mảng A có 8 hàng, 9 cột. Lưu trữ liên tiếp mảng A ưu tiên cột nếu phần tử F(11) có địa chỉ 230 , mỗi phần tử chiếm 3 ô thì phần tử F(37) có địa chỉ:","a":"380"},{"q":"Cho mảng 2 chiều A={a (i j )}, mảng có m hàng, n cột, và được lưu trữ liên tiếp. Công thức tính địa chỉ của phần tử a (i j)\n\nL{ F(i j )} = L(0) + C [(j - 1)m + (i - 1)]\n\nDùng trong trường hợp","a":"Ưu tiên cột"},{"q":"Cho mảng 2 chiều A={a (i j )}, mảng có m hàng, n cột, và được lưu trữ liên tiếp. Công thức tính địa chỉ của phần tử a (i j)\nL{ F(i j )} = L(0) + C [(j - 1)m + (i - 1)]\nDùng trong trường hợp","a":"Ưu tiên cột"},{"q":"Cho mảng một chiều A=(a1,a2,…,ax,…,an) và được lưu trữ liên tiếp. Giả thử mỗi phần tử của mảng chiếm 3 ô và phần tử đầu tiên F(1) có địa chỉ 23 thì phần tử F(4) có địa chỉ","a":"41"},{"q":"Cho một danh sách móc nối với các phần tử trong danh sách có kiểu S1 được định nghĩa như sau:\n\n struct S1{ int info; struct S1 * next;} *head;\n\nBiết con trỏ “head” lưu địa chỉ của phần tử đầu tiên trong danh sách. Cho biết mục đích của câu lệnh sau:\n\n { head- > next- > next- > info=111;};","a":"Giá trị “info” trong phần tử thứ 3 đã bị thay đổi."},{"q":"Cho một danh sách móc nối với các phần tử trong danh sách có kiểu S1 được định nghĩa như sau:\n\n struct S1{ int info; struct S1 * next;} *head;\n\nBiết con trỏ “head” lưu địa chỉ của phần tử đầu tiên trong danh sách. Cho biết mục đích của câu lệnh sau:\n\n {(head- > next)=(head- > next)- > next;};","a":"Loại bỏ phần tử thứ 2 ra khỏi danh sách."},{"q":"Cho một ma trận thưa, hàng 1 có 2 phần tử F(11) , F(12) . Từ hàng thứ 2 chỉ có 3 phần tử F(k , k-1) ; F(k, k) ; F(k, k+1) , hàng cuối cùng cũng chỉ có 2 phần tử : F(n, n-1) ; F(n , n)\nHãy lưu trữ liên tiếp ưu tiên hàng của ma trận này thành một mảng một chiều : thí dụ F(11) là b(1) ; F(12) là b(2) ; F(21) là b(3) …\nTính b(k) nếu phần tử F(i j ) là F(6 , 7)","a":"b(17)"},{"q":"Cho đoạn chương trình sau:\n\nint Logarit(int n)\n\n{\n\n if(n < 0)\n\n return -1;\n\n else\n\n if(n > =2)\n\n return 1+logarit(n/2);\n\n else\n\n return 0;\n\n}\n\nCho biết chức năng của đoạn chương trình trên","a":"Tìm giá trị nguyên  logarit cơ số 2 của n"},{"q":"Cho đoạn chương trình sau:\n\nint dequy(int a,int b)\n\n{\n\n if(a==b)\n\n return a;\n\n else\n\n {\n\n if(a > b)\n\n a=a-b;\n\n else\n\n b=b-a;\n\n }\n\n return dequy(a,b);\n\n}\n\nCho biết chức năng của đoạn chương trình trên","a":"Tìm ước số chung lớn nhất của 2 số nguyên a, b."},{"q":"Cho đoạn chương trình sau:\n\nint dequy(int n)\n\n{\n\n if(n==0)\n\n return 0;\n\n return 1+dequy(n/10);\n\n}\n\nCho biết chức năng của đoạn chương trình trên","a":"Đếm số lượng chữ số nguyên dương n"},{"q":"Cho đoạn chương trình sau:\n\nlong Tong(unsigned n)\n\n{\n\n if(n==0)\n\n return 1;\n\n return n+Tong(n-2);\n\n}\n\nCho biết chức năng của đoạn chương trình trên dùng để tính cho biểu thức nào","a":"S(n)=1+3+5+…+(2.n+1) với n > =0"},{"q":"Cho đoạn chương trình sau:\n\nlong dequy(long n,long &max)\n\n{ \n\n long m;\n\n if(n==0)\n\n return max;\n\n else\n\n {\n\n m=n%10;\n\n if(m > max)\n\n max=m;\n\n } \n\n return dequy(n/10,max);\n\n}\n\nCho biết chức năng của đoạn chương trình trên","a":"Tìm chữ số có giá trị lớn nhất của số nguyên dương n"},{"q":"Cho đoạn chương trình sau:\nint Logarit(int n)\n{\n if(n < 0)\n return -1;\n else\n if(n > =2)\n return 1+logarit(n/2);\n else\n return 0;\n}\nCho biết chức năng của đoạn chương trình trên","a":"Tìm giá trị nguyên  logarit cơ số 2 của n"},{"q":"Cho đoạn chương trình sau:\nint n=0;\nfor (int i=0; i < 10; i+=4) n+=I; giá trị của biến n là","a":"12"},{"q":"Cho đoạn chương trình sau:\nlong Tong(unsigned n)\n{\n if(n==0)\n return 1;\n return n+Tong(n-2);\n}\nCho biết chức năng của đoạn chương trình trên dùng để tính cho biểu thức nào","a":"S(n)=1+3+5+…+(2.n+1) với n > =0"},{"q":"Cho đoạn chương trình sau:\nlong dequy(long n,long &max)\n{ \n long m;\n if(n==0)\n return max;\n else\n {\n m=n%10;\n if(m > max)\n max=m;\n } \n return dequy(n/10,max);\n}\nCho biết chức năng của đoạn chương trình trên","a":"Tìm chữ số có giá trị lớn nhất của số nguyên dương n"},{"q":"Cho đoạn chương trình:\n\nchar S[] = “Helen”;\n\nchar *p = S;\n\nchar c = *(p+3);\n\nGiá trị của c sẽ là:","a":"e"},{"q":"Cho đoạn chương trình:\nchar S[] = “Helen”;\nchar *p = S;\nchar c = *(p+3);\nGiá trị của c sẽ là:","a":"e"},{"q":"Chọn câu trả lời đúng nhất về thuật toán","a":"Thuật toán là một dãy hữu hạn các bước, mỗi bước mô tả chính xác các phép toán hoặc hành động cần thực hiện để giải quyết vấn đề đặt ra"},{"q":"Chọn câu đúng nhất cho hàm Swap?","a":"Void Swap(int &X, int &Y) { \n\n   int Temp = X; X = Y; Y = Temp; \n\n}"},{"q":"Chọn câu đúng?","a":["“struct” là một kiểu dữ liệu do người dùng định nghĩa bao gồm nhiều thành phần có kiểu khác nhau.","“struct” là sự kết hợp của nhiều thành phần có thể có kiểu khác nhau."]},{"q":"Cài đặt danh sách bằng con trỏ có nghĩa là","a":"Dùng con trỏ để liên kết các phần tử của danh sách theo phương thức ai chỉ đến ai+1. Để một phần tử có thể chỉ đến một phần tử khác ta xem mỗi ô là một Record gồm có 2 trường : Trường Elements để giữ nội dung của phần tử trong danh sách. Trường Next là một con trỏ giữ địa chỉ của ô kế tiếp."},{"q":"Cài đặt danh sách bằng mảng có nghiã là","a":"dùng một mảng (array) để lưu trữ liên tiếp các phần tử của danh sách bắt đầu từ vị trí đầu tiên của mảng."},{"q":"Các hoạt động cơ bản trên Danh sách liên kết vòng","a":["Chèn","hiển thị","xóa"]},{"q":"Các thuộc tính của một kiểu dữ liệu","a":"Tất cả các thuộc tính đưa ra"},{"q":"Các tiêu chuẩn đánh giá cấu trúc dữ liệu. Để đánh giá một cấu trúc dữ liệu chúng ta thường dựa vào các tiêu chí nào","a":"Tất cả đáp án trên là đúng"},{"q":"Cây 5 phân có nghĩa là gì?","a":"nut-co-cap-lon-nhat-la-5"},{"q":"Cây nhị phân khác rỗng là cây...","a":"Mỗi nút có không quá 2 nút con"},{"q":"Cây nhị phân tìm kiếm là:","a":"Cây nhị phân mà mỗi nút trong cây đều thoả tính chất: giá trị của nút cha nhỏ hơn mọi nút trên cây con trái và lớn hơn mọi nút trên cây con phảI của nó."},{"q":"Có bao nhiêu loại hoạt động cơ bản trên danh sách liên kết vòng","a":"3"},{"q":"Có mấy loại danh sách liên kết","a":"3"},{"q":"Cấu trúc dữ liệu nào tương ứng với LIFO","a":"stack"},{"q":"Danh sách khai báo bằng con trỏ. Hàm sau có chức năng gì?\n\nBoolean EList( ListvHeader )\n\n{\n\nElist = (Header.Next = Nil);\n\n}","a":"kiem-tra-danh-sach-rong"},{"q":"Danh sách khai báo bằng con trỏ. Hàm sau có chức năng gì?\nBoolean EList( ListvHeader )\n{\nElist = (Header.Next = Nil);\n}","a":"kiem-tra-danh-sach-rong"},{"q":"Danh sách khai báo bằng con trỏ. Thủ tục sau có chức năng gì?\"\n\nvoid MnullList ( List Header)\n\n{\n\nNew (Header);\n\nHeader.Next : = Nil;\n\n}","a":"thu-tuc-khoi-tao-danh-sach-rong"},{"q":"Danh sách khai báo bằng con trỏ. Thủ tục sau có chức năng gì?\"\nvoid MnullList ( List Header)\n{\nNew (Header);\nHeader.Next : = Nil;\n}","a":"thu-tuc-khoi-tao-danh-sach-rong"},{"q":"Danh sách liên kết vòng là gì?\n\n1. Danh sách liên kết vòng (Circular Linked List) là một biến thể của Danh sách liên kết (Linked List), trong đó phần tử đầu tiên trỏ tới phần tử cuối cùng và phần tử cuối cùng trỏ tới phần tử đầu tiên., \n\n2. Danh sách liên kết vòng (Circular Linked List) là một biến thể của Danh sách liên kết (Linked List), trong đó phần tử đầu tiên trỏ tới phần tử đầu tiên và phần tử cuối cùng trỏ tới phần tử cuối.","a":"1 đúng, 2 sai"},{"q":"Danh sách liên kết vòng là gì?\n1. Danh sách liên kết vòng (Circular Linked List) là một biến thể của Danh sách liên kết (Linked List), trong đó phần tử đầu tiên trỏ tới phần tử cuối cùng và phần tử cuối cùng trỏ tới phần tử đầu tiên., \n2. Danh sách liên kết vòng (Circular Linked List) là một biến thể của Danh sách liên kết (Linked List), trong đó phần tử đầu tiên trỏ tới phần tử đầu tiên và phần tử cuối cùng trỏ tới phần tử cuối.","a":"1 đúng, 2 sai"},{"q":"Danh sách liên kết đôi là gì?\n\n1. Là một biến thể của Danh sách liên kết (Linked List), trong đó hoạt động duyệt qua các nút có thể được thực hiện theo hai chiều: về trước và về sau một cách dễ dàng khi so sánh với Danh sách liên kết đơn.\n\n2. Là một biến thể của danh sách liên kết đơn, nhưng do 2 danh sách đơn cộng lại, Không có đáp án nào đúng","a":"1 đúng, 2 sai"},{"q":"Danh sách liên kết đôi là gì?\n1. Là một biến thể của Danh sách liên kết (Linked List), trong đó hoạt động duyệt qua các nút có thể được thực hiện theo hai chiều: về trước và về sau một cách dễ dàng khi so sánh với Danh sách liên kết đơn.\n2. Là một biến thể của danh sách liên kết đơn, nhưng do 2 danh sách đơn cộng lại, Không có đáp án nào đúng","a":"1 đúng, 2 sai"},{"q":"Danh sách tuyến tính dạng ngăn xếp là","a":"Là một danh sách tuyến tính trong đó phép bổ sung một phần tử vào ngăn xếp và phép loại bỏ một phần tử khỏi ngăn xếp luôn luôn thực hiện ở một đầu gọi là đỉnh ."},{"q":"Danh sách tuyến tính là","a":["Danh sách mà quan hệ lân cận giữa các phần tử được hiển thị ra thì được là danh sách tuyến tính","Danh sách mà quan hệ lân cận giữa các phần tử được hiển thị ra thì được là danh sách tuyến tính.","Danh sách mà quan hệ lân cận giữa các phần tử được xác định."]},{"q":"Duyệt cây nhị phân theo thứ tự giữa được thực hiện theo thứ tự:","a":"Duyệt cây con trái theo thứ tự giữa, thăm gốc, duyệt cây con phải theo thứ tự giữa."},{"q":"Duyệt cây nhị phân theo thứ tự sau được thực hiện theo thứ tự:","a":"Duyệt cây con trái theo thứ tự sau, duyệt cây con phải theo thứ tự sau, thăm gốc."},{"q":"Duyệt cây nhị phân theo thứ tự trước được thực hiện theo thứ tự:","a":"Thăm gốc, duyệt cây con trái theo thứ tự trước, duyệt cây con phải theo thứ tự trước."},{"q":"Dãy số Fibonacci bắt nguồn từ bài toán cổ về việc sinh sản của các cặp thỏ. Bài toán được đặt ra như sau:\n\nCác con thỏ không bao giờ chết.\n\nHai tháng sau khi ra đời một cặp thỏ mới sẽ sinh ra một cặp thỏ con.\n\nKhi đã sinh con rồi thì cứ mỗi tháng tiếp theo chúng lại sinh được một cặp con mới.\n\nGiả sử bắt đầu từ một cặp thỏ mới ra đời thì đến tháng thứ 5 sẽ có bao nhiêu cặp?","a":"5 cặp"},{"q":"Dùng STACK để lưu trữ số nhị phân có giá trị bằng số thập phân 215 ta có kết quả: ( số bên trái vào trước số bên phải )","a":"11101011"},{"q":"Dấu hiệu nào dưới đây cho biết danh sách liên kết đơn rỗng:","a":"(p==NULL);"},{"q":"Dấu hiệu nào dưới đây cho biết node p của một danh sách liên kết đơn là node cuối cùng bên phải:","a":"(p-->-next==null);"},{"q":"Dữ liệu kí tự bao gồm","a":["Các kí tự chữ cái.","Các kí tự số chữ số.","Các kí tự đặc biệt."]},{"q":"Giả sử Q là Hàng đợi, các phần tử của nó có kiểu Item. Hàm sau làm nhiệm vụ gì \nboolean F(Queue Q) {\n F = (Q.rear = max);\n}","a":"Kiểm tra hàng đợi đầy"},{"q":"Giả sử có câu lệnh ch='A'. Vậy ch sẽ chứa bao nhiêu byte","a":"1"},{"q":"Giả sử có câu lệnh ch[]= \"A\". ch chứa bao nhiêu bytes","a":"2"},{"q":"Giả sử trong ngôn ngữ C sử dụng khai báo “double a[12]”, phần tử a[7] là phần tử thứ bao nhiêu trong mảng a","a":"Thứ 8."},{"q":"Ho một danh sách móc nối với các phần tử trong danh sách có kiểu S1 được định nghĩa như sau:\n\nstruct S1{int info; struct S1 *next;} *head;\n\nBiết con trỏ “*head” lưu địa chỉ của phần tử đầu tiên trong danh sách. Nhóm câu lệnh nào sau đây thêm một phần tử vào đầu danh sách:","a":"P- > next=head; head=p;"},{"q":"Hàng đợi còn được gọi là danh sách kiểu","a":"fifo"},{"q":"Hàng đợi còn được gọi là danh sách kiểu:","a":"FIFO"},{"q":"Hàng đợi được viết tắt bởi sự kết hợp các từ sau","a":["FI","FO"]},{"q":"Hãy chỉ ra tùy chọn gắn một file vào chương trình hiện tại không hợp lệ dưới đây là","a":"#include-<-file"},{"q":"Khai báo hàm tìm giá trị lớn nhất trong một mảng các số long dưới đây, khai báo đúng là ?","a":"long max(long *a, int n)"},{"q":"Khi biến con trỏ không chứa bất kì một địa chỉ nào thì giá trị của nó sẽ là","a":["0","NULL."]},{"q":"Khi bổ sung một phần tử mới vào hàng đợi cần kiểm tra thì ...","a":"Hàng đợi có đầy không"},{"q":"Khi chèn một phần tử vào danh sách (cài đặt bằng mảng) yêu cầu cần","a":"do-dai-cua-danh-sach-<-do-dai-cua-mang"},{"q":"Khi chèn một phần tử vào danh sách xảy ra tình trạng:\n\nđộ dài của danh sách = độ dài của mảng thì thông báo là:","a":"danh-sach-day"},{"q":"Khi khai báo mảng, ta khởi tạo luôn giá trị của mảng như sau:int x[3]={4,2,6}; Nghĩa là: x[0]=  , x[1]=  , x[2]=  ;","a":"4,2,6"},{"q":"Khi lưu trữ cây nhị phân dưới dạng mảng, nếu vị trí của nút cha trong mảng là 3 thì vị trí tương ứng của nút con phải sẽ là:","a":"7"},{"q":"Khi lưu trữ cây nhị phân dưới dạng mảng, nếu vị trí của nút cha trong mảng là 3 thì vị trí tương ứng của nút con trái sẽ là:","a":"6"},{"q":"Khi lưu trữ cây nhị phân dưới dạng mảng, nếu vị trí của nút cha trong mảng là i thì vị trí của nút con trái là","a":"2*i"},{"q":"Khi lưu trữ cây nhị phân dưới dạng mảng, nếu vị trí của nút cha trong mảng là i thì vị tí của nút con phải là","a":"2*i + 1"},{"q":"Khi thực hiện việc thêm một node x vào cây nhị phân tìm kiếm ta chỉ cần...","a":"Tìm vị trí thích hợp cho x trên toàn bộ cây"},{"q":"Khi đổi một số nguyên từ hệ thập phân sang hệ nhị phân thì người ta dùng phép chia liên tiếp cho 2 và lấy các số dư (là các chữ số nhị phân) theo chiều ngược lại.\n\nCơ chế sắp xếp này chính là cơ chế hoạt động của cấu trúc dữ liệu:","a":"Ngăn xếp (stack)"},{"q":"Khi đổi một số nguyên từ hệ thập phân sang hệ nhị phân thì người ta dùng phép chia liên tiếp cho 2 và lấy các số dư (là các chữ số nhị phân) theo chiều ngược lại.\nCơ chế sắp xếp này chính là cơ chế hoạt động của cấu trúc dữ liệu:","a":"Ngăn xếp (stack)"},{"q":"Không gian nhớ dùng để lưu trữ các node của danh sách liên kết kép:","a":"Lưu trữ rởi rác trong bộ nhớ."},{"q":"Khử đệ quy là gì","a":"Đưa các bài toán đệ quy về các bài toán không sử dụng đệ quy"},{"q":"Kiểu dữ liệu float có thể xử lí dữ liệu trong phạm vi nào","a":"3.4*10-38-den-3.4*1038"},{"q":"Kiểu dữ liệu nào dưới đây được coi là kiểu dữ liệu cơ bản trong ngôn ngữ lập trình C","a":"Kiểu double."},{"q":"Kí hiệu nào là con trỏ của phẩn tử thứ 3 của mảng a có 4 kí tự","a":"*(a+2)"},{"q":"Kích thước của mảng là  hay","a":"so-phan-tu-toi-da-cua-mang,kich-thuoc-bo-nho-se-cap-phat-cho-mang"},{"q":"Kích thước lưu trữ kiểu số nguyên là","a":"2 byte"},{"q":"Kết quả của đoạn chương trình sau là gì:\nchar c;\nint n;\nprintf(\"%d%c\",&n,&c);\nNếu gõ vào : ”10 T”.","a":["c=''.","n=10"]},{"q":"Lựa chọn định nghĩa về danh sách đúng?","a":["Danh sách là tập hợp các phần tử có kiểu dữ liệu xác định và giữa chúng có một mối liên hệ nào đó,","Một danh sách có chiều dài bằng 0 là một danh sách rỗng.","Số phần tử của danh sách gọi là chiều dài của danh sách"]},{"q":"Miền giá trị của Kiểu số nguyên là:","a":"-32768 .. 32767"},{"q":"Mảng là","a":"Một nhóm phần tử có cùng kiểu và chung tên gọi."},{"q":"Mỗi nút trong cây có tối đa:","a":"Nhiều nút con"},{"q":"Một cây nhị phân có chiều cao là 7, cây đó chỉ có 50 nút. Nếu lưu trữ kế tiếp thì lãng phí bao nhiêu ô ( nút gốc có mức 1, mỗi nút chiếm 1 ô ):","a":"77-o"},{"q":"Một danh sách trong đó tất cả các thao tác chèn thực hiện tại một đầu, thao tác xóa được thực hiện tại đầu kia của danh sách gọi là:","a":"cay-nhi-phan."},{"q":"Một giá trị kiểu char chiếm bao nhiêu bộ nhớ","a":"1byte"},{"q":"Ngôn ngữ lập trình C được Dennish phát triển dựa trên ngôn ngữ lập trình nào:","a":["BCPL","Ngôn ngữ B"]},{"q":"Ngôn ngữ lập trình nào dưới đây là ngôn ngữ lập trình có cấu trúc?","a":["Ngôn ngữ C","Pascal"]},{"q":"Ngăn xếp được viết tắt bởi sự kết hợp các từ sau","a":["FO","LI"]},{"q":"Nút có khóa nhỏ nhất trong cây nhị phân tìm kiếm khác rỗng là...","a":"Nút con bên trái  nhất"},{"q":"Nếu S1 và S2 là các câu lệnh và E là biểu thức logic thì\n\nIf E Then S1 Else S2\n\nGiả sử thời gian thực hiện các lệnh S1, S2 là O(f(n)) và O(g(n)) tương ứng. Khi đó thời gian thực hiện lệnh if là","a":"O(max (f()n), g(n)))"},{"q":"Nếu có các khai báo sau:\nchar msg[10];\nchar *ptr;\nchar value;\nCâu nào sau đây là đúng:","a":"ptr=msg;"},{"q":"Nếu hàm được gọi trước khi nó định nghĩa thì điều kiện là gì?","a":"Trước khi gọi hàm nó phải được khai báo"},{"q":"Nếu lưu trữ móc nối thì mỗi nút của cây nhị phân cần 2 khoảng để ghi địa chỉ 2 con. Cây có 72 nút. Vậy lãng phí bao nhiêu khoảng địa chỉ:","a":"73"},{"q":"Nếu x là một biến toàn cục và x không phải là một con trỏ thì:","a":"Miền nhớ giành cho x không bị thay đổi trong quá trình thực hiện chương trình."},{"q":"Phát biểu nào sau đây về mảng một chiều là đúng?","a":"Là tập hợp hữu hạn các phần tử có cùng kiểu dữ liệu"},{"q":"Phương pháp sắp xếp nhanh (Quick sort) chính là phương pháp:","a":"Phân đoạn"},{"q":"Queue (hàng đợi) là kiểu danh sách tuyến tính mà phép loại bỏ thực hiện ở 1 đầu gọi là lối","a":"truoc"},{"q":"Sinh viên tải Tải về . Cho biết đây là giải thuật gì (nhị phân hay tuyến tính)","a":"nhi-phan"},{"q":"Sinh viên tải Tải về . Cho biết đây là giải thuật gì (nhị phân hay tuyến tính)\n<a href=\"https://cms.poly.edu.vn/asset-v1:FPOLY+SOF307+27.02.2020+type@asset+block@Lab4x2.doc\">Tải về</a>","a":"nhi-phan"},{"q":"Sinh viên tải Tải về . Cho biết đây là giải thuật gì (nhị phân hay tuyến tính)?\n<a href=\"https://cms.poly.edu.vn/asset-v1:FPOLY+SOF307+27.02.2020+type@asset+block@Lab4x1.doc\">Tải về</a>","a":"tuyen-tinh"},{"q":"Sinh viên tải Tải về . Cho biết đây là giải thuật gì nhị phân hay tuyến tính.....","a":"Tìm phần tử nhỏ nhất của mảng M bao gồm N phần tử"},{"q":"Sinh viên tải Tải về . Kết quả biến n là","a":"7"},{"q":"Sinh viên tải Tải về . Kết quả biến n là","a":"5"},{"q":"Sinh viên tải Tải về . Kết quả biến n là\n<a href=\"https://cms.poly.edu.vn/asset-v1:FPOLY+SOF307+27.02.2020+type@asset+block@Lab4x13.doc\">Tải về</a>","a":"7"},{"q":"Sinh viên tải Tải về . Kết quả biến n là\n<a href=\"https://cms.poly.edu.vn/asset-v1:FPOLY+SOF307+27.02.2020+type@asset+block@Lab4x15.doc\">Tải về</a>","a":"5"},{"q":"Sinh viên tải Tải về . Kết quả biến n là\n<a href=\"https://cms.poly.edu.vn/asset-v1:FPOLY+SOF307+27.02.2020+type@asset+block@Lab4x17.doc\">Tải về</a>","a":"7"},{"q":"Sinh viên tải Tải về . Kết quả biến result là","a":"3"},{"q":"Sinh viên tải Tải về . Kết quả biến result là","a":"2"},{"q":"Sinh viên tải Tải về . Kết quả biến result là","a":"6"},{"q":"Sinh viên tải Tải về . Kết quả biến result là\n<a href=\"https://cms.poly.edu.vn/asset-v1:FPOLY+SOF307+27.02.2020+type@asset+block@Lab4x12.doc\">Tải về</a>","a":"2"},{"q":"Sinh viên tải Tải về . Tìm mô tả đúng nhất cho hàm TinhTong \n\n1. Hàm tính tổng N số nguyên đầu tiên\n\n2. Hàm tính tổng N số nguyên tố nhỏ hơn N, tính tổng N số nguyên tố lớn hơn N\n<a href=\"https://cms.poly.edu.vn/asset-v1:FPOLY+SOF307+27.02.2020+type@asset+block@Lab4x4.doc\">Tải về</a>","a":"1 sai, 2 sai"},{"q":"Sinh viên tải Tải về . Đáp án đúng nhất?","a":"Hàm thực hiện việc sao chép nội dung mảng M có chiều dài Len về mảng CM có cùng chiều dài. Hàm trả về chiều dài của mảng CM sau khi sao chép."},{"q":"Sinh viên tải Tải về . Đáp án đúng nhất?","a":"Hàm sẽ trả về -1 nế u không tìm thấy phần tử có giá trị là X"},{"q":"Sinh viên tải Tải về . Đáp án đúng nhất?\n<a href=\"https://cms.poly.edu.vn/asset-v1:FPOLY+SOF307+27.02.2020+type@asset+block@Lab4x6.doc\">Tải về</a>","a":"Thủ tục hỗ trợ tìm kiếm đệ quy phần tử có giá trị là X trê n mảng các phần tử từ chỉ s ố từ Firs t đế n chỉ s ố Last"},{"q":"Sinh viên tải file Tải về cho biết chức năng chính của hàm là\n<a href=\"https://cms.poly.edu.vn/asset-v1:FPOLY+SOF307+27.02.2020+type@asset+block@Lab1x15.doc\">Tải về</a>","a":"sap-xep-day-so-tang-dan"},{"q":"Sinh viên tải file Tải về cho biết kết quả của chương trình là","a":"16.67"},{"q":"Sinh viên tải file Tải về cho biết kết quả của chương trình là\n<a href=\"https://cms.poly.edu.vn/asset-v1:FPOLY+SOF307+27.02.2020+type@asset+block@Lab2x1.doc\">Tải về</a>","a":"16.67"},{"q":"Sinh viên tải file Tải về khi nhập n=3 và A[0]: 4, Nhap A[1]: 6, Nhap A[2]: 3, kết quả sẽ là","a":"3,4,6"},{"q":"Sinh viên tải file Tải về khi nhập n=3 và A[0]: 4, Nhap A[1]: 6, Nhap A[2]: 3, kết quả sẽ là\n<a href=\"https://cms.poly.edu.vn/asset-v1:FPOLY+SOF307+27.02.2020+type@asset+block@Lab1x14.doc\">Tải về</a>","a":"3,4,6"},{"q":"Sinh viên tải file Tải về kết quả của chương trình là","a":"66"},{"q":"Sinh viên tải file Tải về kết quả của chương trình là là","a":"llo_world"},{"q":"Sinh viên tải file Tải về kết quả của chương trình là là\n<a href=\"https://cms.poly.edu.vn/asset-v1:FPOLY+SOF307+27.02.2020+type@asset+block@Lab2x11.doc\">Tải về</a>","a":"llo_world"},{"q":"Sinh viên tải file Tải về kết quả của chương trình là?","a":"63.20, -45.60, 70.10, 3.60, 14.50"},{"q":"Sinh viên tải file Tải về kết quả của chương trình là?\n<a href=\"https://cms.poly.edu.vn/asset-v1:FPOLY+SOF307+27.02.2020+type@asset+block@Lab2x7.doc\">Tải về</a>","a":"63.20, -45.60, 70.10, 3.60, 14.50"},{"q":"Sinh viên tải file Tải về lỗi thiếu của khi gọi hàm change() là","a":["&",";"]},{"q":"Sinh viên tải file Tải về lỗi thiếu của khi gọi hàm change() là\n<a href=\"https://cms.poly.edu.vn/asset-v1:FPOLY+SOF307+27.02.2020+type@asset+block@Lab2x5.doc\">Tải về</a>","a":["&",";"]},{"q":"Sinh viên tải file Tải về sau đó cho biết kết quả bang cac so\n<a href=\"https://cms.poly.edu.vn/asset-v1:FPOLY+SOF307+27.02.2020+type@asset+block@Lab1x13.doc\">Tải về</a>","a":"153,370,371,407"},{"q":"Sinh viên tải file Tải về sau đó cho biết kết quả của biến sum1 là","a":"10"},{"q":"Sinh viên tải file Tải về sau đó cho biết kết quả của biến sum1 là\n<a href=\"https://cms.poly.edu.vn/asset-v1:FPOLY+SOF307+27.02.2020+type@asset+block@Lab1x3.doc\">Tải về</a>","a":"10"},{"q":"Sinh viên tải file Tải về sau đó nhập a =12 và b=4 cho biết biến UCLN là","a":"4"},{"q":"Sinh viên tải file Tải về sau đó nhập n =12 và m =12 cho biết biến DC là\n<a href=\"https://cms.poly.edu.vn/asset-v1:FPOLY+SOF307+27.02.2020+type@asset+block@Lab1x11.doc\">Tải về</a>","a":"2"},{"q":"Sinh viên tải file Tải về sau đó nhập n =12 và m =15 cho biết biến DC là","a":"1"},{"q":"Sinh viên tải file Tải về đầu ra output là","a":"hello_world"},{"q":"Sinh viên tải file Tải về đầu ra output là\n<a href=\"https://cms.poly.edu.vn/asset-v1:FPOLY+SOF307+27.02.2020+type@asset+block@Lab2x10.doc\">Tải về</a>","a":"hello_world"},{"q":"Sinh viên tải file Tải về đầu ra output là\n<a href=\"https://cms.poly.edu.vn/asset-v1:FPOLY+SOF307+27.02.2020+type@asset+block@Lab2x9.doc\">Tải về</a>","a":"fpolyhcm.com"},{"q":"Sinh viên tải file Tải về. Cho biết chương trình lỗi dòng thư","a":"17"},{"q":"Sinh viên tải file Tải về. Cho biết chương trình lỗi dòng thư\n<a href=\"https://cms.poly.edu.vn/asset-v1:FPOLY+SOF307+27.02.2020+type@asset+block@Lab3x12.doc\">Tải về</a>","a":"17"},{"q":"Sinh viên tải file Tải về. Cho biết chương trình trên lỗi ở dòng","a":"19"},{"q":"Sinh viên tải file Tải về. Cho biết chương trình trên lỗi ở dòng\n<a href=\"https://cms.poly.edu.vn/asset-v1:FPOLY+SOF307+27.02.2020+type@asset+block@Lab3x10.doc\">Tải về</a>","a":"19"},{"q":"Sinh viên tải file Tải về. Cho biết chương trình trên lỗi ở dòng\n<a href=\"https://cms.poly.edu.vn/asset-v1:FPOLY+SOF307+27.02.2020+type@asset+block@Lab3x9.doc\">Tải về</a>","a":"19"},{"q":"Sinh viên tải file Tải về. Cho biết kết quả của biến n là\n<a href=\"https://cms.poly.edu.vn/asset-v1:FPOLY+SOF307+27.02.2020+type@asset+block@Lab3x1.doc\">Tải về</a>","a":"5"},{"q":"Sinh viên tải file Tải về. Khi kết quả n=24 thì ta phải nhập a=","a":"4"},{"q":"Sinh viên tải file Tải về. Khi kết quả n=24 thì ta phải nhập a=\n<a href=\"https://cms.poly.edu.vn/asset-v1:FPOLY+SOF307+27.02.2020+type@asset+block@Lab3x8.doc\">Tải về</a>","a":"4"},{"q":"Sinh viên tải file Tải về. Khi nhập a=10; và i=2 thì biến b là =","a":"8"},{"q":"Sinh viên tải file Tải về. Khi nhập a=10; và i=2 thì biến b là =","a":"2"},{"q":"Sinh viên tải file Tải về. Khi nhập a=6; b=8 thì i là","a":"2"},{"q":"Sinh viên tải file Tải về. Khi nhập a=6; b=8 thì i là\n<a href=\"https://cms.poly.edu.vn/asset-v1:FPOLY+SOF307+27.02.2020+type@asset+block@Lab3x2.doc\">Tải về</a>","a":"2"},{"q":"Sinh viên tải file Tải về. Khi nhập vào số 4, kết quả của chương trình là\n<a href=\"https://cms.poly.edu.vn/asset-v1:FPOLY+SOF307+27.02.2020+type@asset+block@Lab3x11.doc\">Tải về</a>","a":"10"},{"q":"Sinh viên tải file Tải về. Sinh viên cho biết lỗi dòng thứ mấy","a":"21"},{"q":"Sinh viên tải file Tải về. Sinh viên cho biết lỗi dòng thứ mấy","a":"15"},{"q":"Sinh viên tải file Tải về. Sinh viên cho biết lỗi dòng thứ mấy\n<a href=\"https://cms.poly.edu.vn/asset-v1:FPOLY+SOF307+27.02.2020+type@asset+block@Lab3x4.doc\">Tải về</a>","a":"21"},{"q":"Sinh viên tải file Tải về. Sinh viên cho biết lỗi dòng thứ mấy\n<a href=\"https://cms.poly.edu.vn/asset-v1:FPOLY+SOF307+27.02.2020+type@asset+block@Lab3x6.doc\">Tải về</a>","a":"10"},{"q":"Sắp xếp theo thứ tự tăng dần của cấp thời gian thực hiện chương trình (Chú ý: (log2n) = Log cơ số 2 của n)","a":"O(1),O(log2n),O(n),O(nlog2n)"},{"q":"Số phép so sánh của thuật toán tìm kiếm, trong trường hợp xấu nhất là","a":"2*n"},{"q":"Tham chiếu đến phần tử thứ i của mảng D được xác định bởi","a":"D[i]"},{"q":"Thao tác POP(x) dùng trong Stack là để:","a":"Lấy một phần tử cuối cùng ra khỏi đỉnh Stack"},{"q":"Thao tác Push(x) dùng trong Stack là để:","a":"Bổ sung một phần tử vào đỉnh Stack"},{"q":"Thành phần dữ liệu của danh sách liên liên kết .....","a":"Lưu thông tin về bản thân phần tử"},{"q":"Thành phần liên kết của danh sách liên kết .....","a":"Lưu địa chỉ phần tử đứng  sau trong danh sách hoặc bằng NULL nếu là phần  tử cuối danh sách"},{"q":"Thời gian chạy chương trình phụ thuộc vào các yếu tố nào","a":["Dữ liệu đầu vào.","Tính chất của trình biên dịch được dùng.","Tôc độ của máy được dùng.","Độ phức tạp tính toán của giải thuật."]},{"q":"Thời gian thực hiện các lệnh đơn : gán, đọc, viết là  \n\nChú ý: (log2n) = Log cơ số 2 của n; n^2 = n mũ 2","a":"o(1)"},{"q":"Trong biểu diễn dữ liệu dưới dạng cây, cấp của cây chính","a":"Cấp cao nhất của một nút trên cây"},{"q":"Trong biểu diễn dữ liệu dưới dạng cây, nút có cấp bằng 0 gọi là:","a":"Lá"},{"q":"Trong các cấu trúc dữ liệu sau đâu là dữ liệu trừu tượng","a":["Cấu trúc dữ liệu dạng (StacK)","Cấu trúc dữ liệu dạng danh sách(LIST)","Cấu trúc dữ liệu kiểu hàng đợi(QUEUE)"]},{"q":"Trong các cấu trúc dữ liệu sau đâu là dữ liệu trừu tượng","a":["Cấu trúc dữ liệu dạng StacK","Cấu trúc dữ liệu dạng danh sách(LIST)","Cấu trúc dữ liệu kiểu hàng đợi(QUEUE)"]},{"q":"Trong các cấu trúc dữ liệu sau đâu là dữ liệu trừu tượng","a":["Cấu trúc dữ liệu dạng danh sách(LIST)","Cấu trúc dữ liệu kiểu hàng đợi(QUEUE)"]},{"q":"Trong các cấu trúc dữ liệu sau, đâu là dữ liệu trừu tượng?","a":"Tất cả cấu trúc"},{"q":"Trong lưu trữ dữ liệu kiểu Queue (Q) dưới dạng mảng nối vòng, giả sử F là con trỏ trỏ tới lối trước của Q, R là con trỏ trỏ tới lối sau của Q. Điều kiện F=R=0 nghĩa là:","a":"Queue rỗng"},{"q":"Trong lưu trữ dữ liệu kiểu Queue (Q), giả sử F là con trỏ trỏ tới lối trước của Q, R là con trỏ trỏ tới lối sau của Q. Khi loại bỏ một phần tử vào Queue, thì R và F thay đổi thế nào?","a":"F=F+1, R không thay đổi"},{"q":"Trong lưu trữ dữ liệu kiểu Queue (Q), giả sử F là con trỏ trỏ tới lối trước của Q, R là con trỏ trỏ tới lối sau của Q. Khi thêm một phần tử vào Queue, thì R và F thay đổi thế nào?","a":"F không thay đổi, R=R+1"},{"q":"Trong một chương trình có 3 bước thực hiện mà thời gian thực hiện tưng bước lần lượt là O(n2), O(n3) và O(nlog2n). thời gian thực hiện chương trình sẽ là\n\nChú ý: (log2n) = Log cơ số 2 của n; n^2 = n mũ 2","a":"O(n^3)"},{"q":"Trong một chương trình có 3 bước thực hiện mà thời gian thực hiện tưng bước lần lượt là O(n2), O(n3) và O(nlog2n). thời gian thực hiện chương trình sẽ là\nChú ý: (log2n) = Log cơ số 2 của n; n^2 = n mũ 2","a":"O(n^3)"},{"q":"Trong số các phép toán sau đây, phép toán nào không được dùng đối với mảng:","a":"Bổ xung một phần tử vào mảng"},{"q":"Trường hợp cơ sở của giải thuật đệ quy là","a":"trường hợp bài toán Pn, có quy mô đủ nhỏ để ta có thể giải trực tiếp."},{"q":"Trường hợp đệ quy của giải thuật đệ qui là","a":"là cơ chế đưa bài toán cần giải về một hay nhiều bài toán tương tự nhưng có quy mô nhỏ hơn"},{"q":"Tìm mô tả đúng cho hàm sau:\nint SC (int M[], int Len, int CM[]) { \n for (int i = 0; i  <  Len; i++)\n CM[i] = M[i];\n return (Len);\n}","a":"Hàm thực hiện việc sao chép nội dung mảng M có chiều dài Len về mảng CM có cùng chiều dài. Hàm trả về chiều dài của mảng CM sau khi sao chép"},{"q":"Tính chất nào sau đây là tính chất của cây nhị phân tìm kiếm:","a":"Mọi khóa thuộc cây con trái nút đó đều nhỏ hơn khóa ứng với nút đó"},{"q":"Tính chất nào sau đây là tính chất của cây nhị phân tìm kiếm?","a":"Mọi khóa thuộc cây con phải nút đó đều lớn hơn khóa ứng với nút đó"},{"q":"Tư tưởng của giải thuật tìm kiếm trên cây nhị phân tìm kiếm","a":"Tìm kiếm dựa vào cây nhị tìm kiếm: Nừu giá trị cần tìm nhỏ hơn gốc thì thực hiện tìm kiếm trên cây con trái, ngược lại ta việc tìm kiếm được thực hiện trên cây con phải."},{"q":"Tải file Tải về cho biết kết quả của chương trình","a":"24 la so chan\n31 la so le"},{"q":"Tải file Tải về cho biết kết quả của hàm main()","a":"4.898980"},{"q":"Với Stack được cài đặt bằng mảng, thủ tục sau để làm gì?\nvoid MNullStack (Stack s) {\n S.Top =Maxlenght + 1;\n}","a":"Thủ tục khởi tạo Stack rỗng"},{"q":"char S[20]=\"aaaaaea\";\nchar* p=strstr(S,\"e\");\nNếu địa chỉ của S là 1000, thì giá trị của p là bao nhiêu là","a":"1005"},{"q":"cho dãy số 27 40 -7 5 57, thực hiện bước thứ 1, khi áp dụng thuật toán sắp xếp lựa chọn để sắp xếp dãy theo thứ tự giảm, ta có được dãy mới là gì?","a":"57  27 -7  5  40"},{"q":"hàng đợi còn được gọi là danh sách kiểu","a":"fifo"},{"q":"không phải lúc nào cũng có thể xây dựng bài toán theo giải thuật và thủ tục đệ quy một cách dễ dàng, các vấn đề có thể là","a":["Làm thế nào để đảm bảo kích thước bài toán giảm đi sau mỗi lần gọi?","Xem xét và định nghĩa các trường hợp đặc biệt (trường hợp suy biến) như thế nào?"]},{"q":"Ý tưởng của giải thuật tìm kiếm nhị phân:","a":"Tại mỗi bước tiến hành so sánh X với phần tử ở giữa của dãy,Dựa vào bước so sánh này quyết định giới hạn dãy tìm kiếm nằm ở nửa trên, hay nửa dưới của dãy hiện hành."},{"q":"Ý tưởng phương pháp sắp xếp Trộn (Merge sort) là:","a":"Phân đoạn dãy thành nhiều dãy con và lần lượt trộn hai dãy con thành dãy lớn hơn, cho đến khi thu được dãy ban đầu đã được sắp xếp."},{"q":"Ý tưởng phương pháp sắp xếp chọn tăng dần (select sort)","a":"Phân đoạn dãy thành nhiều dãy con và lần lượt trộn hai dãy con thành dãy lớn hơn, cho đến khi thu được dãy ban đầu đã được sắp xếp."},{"q":"Ý tưởng phương pháp sắp xếp nổi bọt (bubble sort) là:","a":"Bắt đầu từ cuối dãy đến đầu dãy, ta lần lượt so sánh hai phần tử kế tiếp nhau, nếu phần tử nào nhỏ hơn được đứng vị trí trên."},{"q":"Ý tưởng phương pháp sắp xếp vun đống (Heap sort) là","a":"Lần lượt tạo đống cho cây nhị phân (phần tử gốc có giá trị lớn nhất) và loại phần tử gốc ra khỏi cây đưa vào dãy sắp xếp."},{"q":"ý tưởng phương pháp sắp xếp chèn (insertion sort) là:","a":"Lần lượt lấy phần tử của danh sách chèn vị trí thích hợp của nó trong dãy bằng cách đẩy các phần tử lớn hơn xuống."},{"q":"ý tưởng phương pháp sắp xếp chọn tăng dần (select sort)","a":"Phân đoạn dãy thành nhiều dãy con và lần lượt trộn hai dãy con thành dãy lớn hơn, cho đến khi thu được dãy ban đầu đã được sắp xếp."},{"q":"ý tưởng phương pháp sắp xếp nhanh (Quick sort) là:","a":"Lần lượt chia dãy phần tử thành hai dãy con bởi một phần tử khoá (dãy con trước khoá gồm các phần tử nhỏ hơn khoá và dãy còn lại gồm các phần tử lớn hơn khoá)."},{"q":"ý tưởng phương pháp sắp xếp vun đống (Heap sort) là","a":"Lần lượt tạo đống cho cây nhị phân (phần tử gốc có giá trị lớn nhất) và loại phần tử gốc ra khỏi cây đưa vào dãy sắp xếp."},{"q":"Đâu là kiểu dữ liệu có cấu trúc?","a":["Kiểu array (mảng)","Kiểu con trỏ"]},{"q":"Đâu là phát biểu dúng về danh sach moc nối:","a":"Các phần tử của nó được lưu trữ rải rác trong bộ nhớ RAM."},{"q":"Đâu là phát biểu đúng về danh sách","a":"Có thể xóa một phần tử tại vị trí bất kì trong danh sách."},{"q":"Đặc trưng của thuật toán","a":"Tất cả ý nêu ra"},{"q":"Đặc trưng nào của thuật toán thể hiện: Tất cả các phép toán có mặt trong các bước của thuật toán phải đủ đơn giản","a":"Tính khả thi"},{"q":"Đặc điểm của giải thuật đệ quy","a":["Có một trường hợp đặc biệt, trường hợp suy biến Khi trường hợp này xảy ra thì bài toán còn lại sẽ được giải quyết theo một cách khác","Sau mỗi lần có lời gọi đệ quy thì kích thước của bài toán được thu nhỏ hơn trước.","Trong thủ tục đệ quy có lời gọi đến chính thủ tục đó"]},{"q":"Để cài đặt Stack ta có thể dùng phương pháp nào sau đây?","a":"Bằng con trỏ và bằng mảng"},{"q":"Để dùng danh sách liên kết, xét hai khai báo sau(cần 1KB để lưu dữ thông tin về một sinh viên):\n\n1- Khai báo 1: struct SV{ thongtin; struct SV *tiep;};\n\n2- Khai báo 2: struct SV {thongtin}; struct DS{struct SV* sv; struct DS* tiep;};\n\n(Với “thongtin” là một thành phần dữ liệu của cấu trúc); Chọn câu đúng nhất trong các câu sau:","a":"Khai báo 2 sẽ giúp chương trình chạy nhanh hơn khi đổi vị trí 2 sinh viên."},{"q":"Để thêm một đối tượng x bất kỳ vào Stack, thao tác thường dùng là:","a":"PUSH(x)."},{"q":"Để tạo danh sách liên kết, theo bạn sinh viên nào dưới đây là khai báo đúng cấu trúc tự trỏ sẽ được dùng:\n\n1- Sinh viên 1:\n\nstruct SV{char ht[25]; int tuoi; struct Sv *tiep;};\n\n2- Sinh viên 2:\n\ntypedef\n\n struct SV node;\n\nstruct SV{char ht[25]; int tuoi; node *tiep;};\n\n3- Sinh viên 3:\n\ntypedef\n\n struct SV{char ht[25]; int tuoi; struct SV *tiep;} node;","a":["1","2","3"]},{"q":"Để tạo danh sách liên kết, theo bạn sinh viên nào dưới đây là khai báo đúng cấu trúc tự trỏ sẽ được dùng:\n1- Sinh viên 1:\nstruct SV{char ht[25]; int tuoi; struct Sv *tiep;};\n2- Sinh viên 2:\ntypedef\n struct SV node;\nstruct SV{char ht[25]; int tuoi; node *tiep;};\n3- Sinh viên 3:\ntypedef\n struct SV{char ht[25]; int tuoi; struct SV *tiep;} node;","a":["1","2","3"]},{"q":"Để đổi chỗ 2 phần tử a7, a9 ta đưa thêm một tham số X và ta thực hiện dãy lệnh sau đây","a":"X=a7 ; a7=a9 ; a9=X"},{"q":"Định nghĩa cấu trúc dữ liệu dạng danh sách (LIST)?","a":"Danh sách là một tập hợp các phần tử có cùng một kiểu mà ta gọi là kiểu phần tử (ElementType)."},{"q":"Định nghĩa danh sách tuyến tính Hàng đợi (Queue)?","a":"Hàng đợi là kiểu danh sách tuyến tính trong đó, phép bổ sung một phần tử vào hàng đợi được thực hiện ở một đầu, gọi là lối sau (rear) và phép loại bỏ một phần tử được thực hiện ở đầu kia, gọi là lối trước (front)."},{"q":"Độ cao của cây là gì?","a":"muc-lon-nhat-cua-cay"},{"q":"Độ phức tạp của giải thuật tìm kiếm nhị phân là:","a":"O(log2N)"},{"q":"Độ phức tạp của giải thuật tìm kiếm tuần tự là:","a":"O(N)"},{"q":"Ưu điểm của thủ tục đệ quy là","a":"Tất cả các đáp trên"},{"q":"Ưu điểm của việc cài đặt danh sách bằng mảng là gì?\n\n1. Khi khai báo một mảng ta phải xác định số lượng phần tử của mảng, nên khống chế số luợng của đối tuợng mà danh sách lưu trữ.\n\n2. Việc truy nhập vào phần tử của mảng được thực hiện trực tiếp dựa vào địa chỉ tính được(chỉ số), nên tốc độ nhanh và đồng đều đối với mọi phần tử.","a":"1 sai, 2 đúng"},{"q":"Ứng dụng của giải thuật đệ quy để giải các bài toán sau:","a":["Tìm kiếm trong danh sách liên kết","Tính giai thừa của số nguyên n","tháp Hà Nội"]},{"q":"Cho một ma trận thưa, hàng 1 có 2 phần tử F(11) , F(12) . Từ hàng thứ 2 chỉ có 3 phần tử F(k , k-1) ; F(k, k) ; F(k, k+1) , hàng cuối cùng cũng chỉ có 2 phần tử : F(n, n-1) ; F(n , n)\n\nHãy lưu trữ liên tiếp ưu tiên hàng của ma trận này thành một mảng một chiều : thí dụ F(11) là b(1) ; F(12) là b(2) ; F(21) là b(3) …\n\nNếu F(67) thì b(  )","a":"17"},{"q":"Cho dãy khoá 42,23,74,11,65,58,94,36\n\nLần lượt đưa dãy khoá trên vào cây nhị phân tìm kiếm. Bây giờ ta muốn tìm kiếm xem trong dãy khoá trên có khoá 105 không thì phải làm bao nhiêu phép so sánh:","a":"3"},{"q":"Danh sách tuyến tính là","a":"Danh sách mà quan hệ lân cận giữa các phần tử được xác định."},{"q":"Danh sách tuyến tính là","a":"Danh sách mà quan hệ lân cận giữa các phần tử được hiển thị ra thì được là danh sách tuyến tính"},{"q":"Sinh viên tải file Tải về sau đó nhập a =12 và b=4 cho biết biến UCLN là\n<a href=\"https://cms.poly.edu.vn/asset-v1:FPOLY+SOF307+27.02.2020+type@asset+block@Lab1x6.doc\">Tải về</a>","a":"4"},{"q":"Tải file Tải về cho biết kết quả của hàm main()\n<a href=\"https://cms.poly.edu.vn/asset-v1:FPOLY+SOF307+27.02.2020+type@asset+block@Lab1x1.doc\">Tải về</a>","a":"4.898980"},{"q":"Sinh viên tải Tải về . Kết quả biến n là\n<a href=\"https://cms.poly.edu.vn/asset-v1:FPOLY+SOF307+27.02.2020+type@asset+block@Lab4x11.doc\">Tải về</a>","a":"5"},{"q":"Sinh viên tải file Tải về. Sinh viên cho biết lỗi dòng thứ mấy\n<a href=\"https://cms.poly.edu.vn/asset-v1:FPOLY+SOF307+27.02.2020+type@asset+block@Lab3x5.doc\">Tải về</a>","a":"15"},{"q":"Tải file Tải về cho biết kết quả của chương trình\n<a href=\"https://cms.poly.edu.vn/asset-v1:FPOLY+SOF307+27.02.2020+type@asset+block@Lab1x2.doc\">Tải về</a>","a":"24 la so chan\n31 la so le"},{"q":"Sinh viên tải Tải về . Đáp án đúng nhất?\n<a href=\"https://cms.poly.edu.vn/asset-v1:FPOLY+SOF307+27.02.2020+type@asset+block@Lab4x5.doc\">Tải về</a>","a":"Hàm sẽ trả về -1 nế u không tìm thấy phần tử có giá trị là X"}]